discovery/__init__.py
discovery/api.py
discovery/apps.py
discovery/bsd-new.LICENSE
discovery/command.py
discovery/debutils.py
discovery/ls.py
discovery/models.py
discovery/route.py
discovery/rsync.py
discovery/saneyaml.py
discovery/seed.py
discovery/utils.py
discovery/utils_test.py
discovery/utils_test.py.ABOUT
discovery/utils_test.py.NOTICE
discovery/version.py
discovery/management/__init__.py
discovery/management/commands/__init__.py
discovery/management/commands/check_licenses.py
discovery/management/commands/check_uri.py
discovery/management/commands/dump_purls.py
discovery/management/commands/get_status.py
discovery/management/commands/remap.py
discovery/management/commands/run_map.py
discovery/management/commands/run_visit.py
discovery/management/commands/seed.py
discovery/mappers/__init__.py
discovery/mappers/debian.py
discovery/mappers/freebsd.py
discovery/mappers/maven.py
discovery/mappers/npm.py
discovery/mappers/pypi.py
discovery/mappers/rubygems.py
discovery/mappers/sourceforge.py
discovery/mappings/__init__.py
discovery/mappings/pypi_trove.py
discovery/migrations/0001_initial.py
discovery/migrations/0002_auto_20160707_1249.py
discovery/migrations/0003_auto_20160712_1223.py
discovery/migrations/0004_auto_20160713_1731.py
discovery/migrations/0005_resourceuri_metadata.py
discovery/migrations/0006_remove_resourceuri_metadata.py
discovery/migrations/0007_change_unique_constraints_on_resourceuri.py
discovery/migrations/0008_change_default_sort_order_on_resourceuri.py
discovery/migrations/0009_resourceuri_source_uri.py
discovery/migrations/0010_resourceuri_mining_level.py
discovery/migrations/0011_auto_20170807_0253.py
discovery/migrations/0012_auto_20170807_0444.py
discovery/migrations/0013_auto_20170807_0511.py
discovery/migrations/0014_auto_20170807_0529.py
discovery/migrations/0015_auto_20180607_0851.py
discovery/migrations/0016_remove_resourceuri_sig.py
discovery/migrations/0017_auto_20180619_2236.py
discovery/migrations/0018_scannableuri_package_id.py
minecode-2.0.0.dist-info/AUTHORS.rst
minecode-2.0.0.dist-info/CHANGELOG.rst
minecode-2.0.0.dist-info/METADATA
minecode-2.0.0.dist-info/NOTICE
minecode-2.0.0.dist-info/README.rst
minecode-2.0.0.dist-info/WHEEL
minecode-2.0.0.dist-info/apache-2.0.LICENSE
minecode-2.0.0.dist-info/cc-by-sa-4.0.LICENSE
minecode-2.0.0.dist-info/top_level.txt
minecode-2.0.0.dist-info/RECORD
